Metadata-Version: 2.1
Name: whizzml-kernel
Version: 0.1.1
Summary: Simple WhizzML kernel for Jupyter
Home-page: https://github.com/whizzml/whizzml_kernel
Author: BigML Team
Author-email: bindings@bigml.com
Classifier: Intended Audience :: Developers
Classifier: License :: OSI Approved :: BSD License
Classifier: Programming Language :: Python :: 3
License-File: LICENSE
